tau_clients/__init__.py
tau_clients/decoders.py
tau_clients/exceptions.py
tau_clients/parsers.py
tau_clients/nsx_defender/__init__.py
tau_clients-0.3.4.data/scripts/download_artifacts.py
tau_clients-0.3.4.data/scripts/download_event_pcaps.py
tau_clients-0.3.4.data/scripts/submit_samples.py
tau_clients-0.3.4.dist-info/licenses/LICENSE
tau_clients-0.3.4.dist-info/licenses/NOTICE
tau_clients-0.3.4.dist-info/METADATA
tau_clients-0.3.4.dist-info/WHEEL
tau_clients-0.3.4.dist-info/top_level.txt
tau_clients-0.3.4.dist-info/RECORD
