Metadata-Version: 2.4
Name: tau-clients
Version: 0.3.4
Summary: Set of clients to interface with various VMware products
Home-page: https://github.com/vmware-samples/tau-clients
Author: Stefano Ortolani
Project-URL: Bug Tracker, https://github.com/vmware-samples/tau-clients/issues
Classifier: Development Status :: 3 - Alpha
Classifier: Intended Audience :: Developers
Classifier: License :: OSI Approved :: BSD License
Classifier: Programming Language :: Python :: 3
Classifier: Operating System :: OS Independent
Classifier: Topic :: Security
Classifier: Topic :: Software Development :: Libraries :: Python Modules
Requires-Python: >=3.9
License-File: LICENSE
License-File: NOTICE
Requires-Dist: more-itertools
Requires-Dist: requests
Requires-Dist: vt-py
Provides-Extra: misp
Requires-Dist: pymisp; extra == "misp"
Dynamic: license-file
